deployment_package-0.0.10.data/data/test_data/test.pkl
deployment_utils/__init__.py
deployment_utils/src/__init__.py
deployment_utils/src/preprocessing.py
deployment_utils/src/schemas.py
deployment_utils/src/__pycache__/__init__.cpython-310.pyc
deployment_utils/src/__pycache__/preprocessing.cpython-310.pyc
deployment_utils/test/__init__.py
deployment_utils/test/testing.py
deployment_utils/test/data/test.pkl
deployment_package-0.0.10.dist-info/METADATA
deployment_package-0.0.10.dist-info/WHEEL
deployment_package-0.0.10.dist-info/top_level.txt
deployment_package-0.0.10.dist-info/RECORD
