Metadata-Version: 2.1
Name: deployment-package
Version: 0.0.10
Summary: Package for preprocessing functions used during Model Deployment module
Home-page: https://github.com/davidbognar201/Model_deployment_package
Author: David Bognar
Author-email: david.bognar@gmail.com
Requires-Python: >=3.8
Requires-Dist: bson
Requires-Dist: pandas
Requires-Dist: scikit-learn
Requires-Dist: numpy
Requires-Dist: pydantic
Provides-Extra: dev
Requires-Dist: pytest ; extra == 'dev'
Requires-Dist: twine ; extra == 'dev'
